[
    {
        "Id": 1,
        "title": "Leaf Rake",
        "introduction": "GDN-0011",
        "modified": "March 19, 2016",
        "topic": "Leaf rake with 48-inch wooden handle.",
        "creator": "Alexey",
        "content": "http://openclipart.org/image/300px/svg_to_png/26215/Anonymous_Leaf_Rake.png"
    },
    {
        "Id": 2,
        "title": "Garden Cart",
        "introduction": "GDN-0023",
        "modified": "March 18, 2016",
        "topic": "15 gallon capacity rolling garden cart",
        "creator": "Alexey",
        "content": "http://openclipart.org/image/300px/svg_to_png/26215/Anonymous_Leaf_Rake.png"
    },
    {
        "Id": 5,
        "title": "Hammer",
        "introduction": "TBX-0048",
        "modified": "May 21, 2016",
        "topic": "Curved claw steel hammer",
        "creator": "Alexey",
        "content": "http://openclipart.org/image/300px/svg_to_png/73/rejon_Hammer.png"
    },
    {
        "Id": 8,
        "title": "Saw",
        "introduction": "TBX-0022",
        "modified": "May 15, 2016",
        "topic": "15-inch steel blade hand saw",
        "creator": "Alexey",
        "content": "http://openclipart.org/image/300px/svg_to_png/27070/egore911_saw.png"
    },
    {
        "Id": 10,
        "title": "Video Game Controller",
        "introduction": "GMG-0042",
        "modified": "October 15, 2015",
        "topic": "Standard two-button video game controller",
        "creator": "Alexey",
        "content": "http://openclipart.org/image/300px/svg_to_png/120337/xbox-controller_01.png"
    }
]